civicrm_py/__init__.py
civicrm_py/contrib/__init__.py
civicrm_py/contrib/asgi.py
civicrm_py/contrib/base.py
civicrm_py/contrib/bottle/__init__.py
civicrm_py/contrib/django/__init__.py
civicrm_py/contrib/django/admin.py
civicrm_py/contrib/django/apps.py
civicrm_py/contrib/django/management/__init__.py
civicrm_py/contrib/django/management/commands/__init__.py
civicrm_py/contrib/django/management/commands/civi_check.py
civicrm_py/contrib/django/management/commands/civi_shell.py
civicrm_py/contrib/django/management/commands/sync_civi.py
civicrm_py/contrib/django/middleware.py
civicrm_py/contrib/django/settings.py
civicrm_py/contrib/django/templates/civi_py/contact_card.html
civicrm_py/contrib/django/templates/civi_py/contact_list.html
civicrm_py/contrib/django/templatetags/__init__.py
civicrm_py/contrib/django/templatetags/civi_tags.py
civicrm_py/contrib/django/webui/__init__.py
civicrm_py/contrib/django/webui/config.py
civicrm_py/contrib/django/webui/templatetags/__init__.py
civicrm_py/contrib/django/webui/templatetags/civi_webui_tags.py
civicrm_py/contrib/django/webui/urls.py
civicrm_py/contrib/django/webui/views.py
civicrm_py/contrib/falcon/__init__.py
civicrm_py/contrib/fastapi/__init__.py
civicrm_py/contrib/flask/__init__.py
civicrm_py/contrib/flask/cli.py
civicrm_py/contrib/integration.py
civicrm_py/contrib/litestar/__init__.py
civicrm_py/contrib/litestar/cli.py
civicrm_py/contrib/litestar/config.py
civicrm_py/contrib/litestar/dependencies.py
civicrm_py/contrib/litestar/dto.py
civicrm_py/contrib/litestar/health.py
civicrm_py/contrib/litestar/plugin.py
civicrm_py/contrib/litestar/routes.py
civicrm_py/contrib/litestar/sqlspec_integration.py
civicrm_py/contrib/litestar/webui/__init__.py
civicrm_py/contrib/litestar/webui/config.py
civicrm_py/contrib/litestar/webui/controllers.py
civicrm_py/contrib/litestar/workflows_integration.py
civicrm_py/contrib/quart/__init__.py
civicrm_py/contrib/registry.py
civicrm_py/contrib/sanic/__init__.py
civicrm_py-0.1.2.dist-info/WHEEL
civicrm_py-0.1.2.dist-info/METADATA
civicrm_py-0.1.2.dist-info/RECORD
