Metadata-Version: 2.4
Name: civicrm-py
Version: 0.1.2
Summary: Modern Python client for CiviCRM API v4 with web framework integration
Keywords: civicrm,api,client,crm,nonprofit,async,msgspec
Author: Jacob Coffee
Author-email: Jacob Coffee <jacob@tomodachi.dev>
License-Expression: MIT
Classifier: Development Status :: 3 - Alpha
Classifier: Environment :: Web Environment
Classifier: Framework :: AsyncIO
Classifier: Intended Audience :: Developers
Classifier: License :: OSI Approved :: MIT License
Classifier: Natural Language :: English
Classifier: Operating System :: OS Independent
Classifier: Programming Language :: Python :: 3
Classifier: Programming Language :: Python :: 3.11
Classifier: Programming Language :: Python :: 3.12
Classifier: Programming Language :: Python :: 3.13
Classifier: Topic :: Internet :: WWW/HTTP
Classifier: Topic :: Software Development :: Libraries :: Python Modules
Classifier: Typing :: Typed
Requires-Dist: httpx>=0.28.0
Requires-Dist: msgspec>=0.19.0
Requires-Dist: django>=4.2 ; extra == 'django'
Requires-Dist: fastapi>=0.115.0 ; extra == 'fastapi'
Requires-Dist: flask>=2.0 ; extra == 'flask'
Requires-Dist: litestar>=2.0 ; extra == 'litestar'
Requires-Dist: jinja2>=3.0 ; extra == 'litestar'
Requires-Dist: sqlspec[asyncpg,aiosqlite]>=0.1.0 ; extra == 'sqlspec'
Requires-Dist: starlette>=0.27.0 ; extra == 'starlette'
Requires-Dist: litestar-workflows>=0.1.0 ; extra == 'workflows'
Maintainer: Jacob Coffee
Maintainer-email: Jacob Coffee <jacob@tomodachi.dev>
Requires-Python: >=3.11
Project-URL: Changelog, https://github.com/JacobCoffee/civi-py/blob/main/CHANGELOG.md
Project-URL: Documentation, https://civi.scriptr.dev
Project-URL: Homepage, https://github.com/JacobCoffee/civi-py
Project-URL: Issues, https://github.com/JacobCoffee/civi-py/issues
Project-URL: Repository, https://github.com/JacobCoffee/civi-py
Provides-Extra: django
Provides-Extra: fastapi
Provides-Extra: flask
Provides-Extra: litestar
Provides-Extra: sqlspec
Provides-Extra: starlette
Provides-Extra: workflows
